regxtools/RegGen.py
regxtools/__init__.py
regxtools/__main__.py
regxtools/__version__.py
regxtools/main.py
regxtools/regxgen/__init__.py
regxtools/regxgen/module.py
regxtools/regxlib/__init__.py
regxtools/regxlib/module.py
regxtools/regxtool/__init__.py
regxtools/regxtool/module.py
regxtools-1.0.10.dist-info/LICENSE
regxtools-1.0.10.dist-info/METADATA
regxtools-1.0.10.dist-info/WHEEL
regxtools-1.0.10.dist-info/top_level.txt
regxtools-1.0.10.dist-info/RECORD
