Metadata-Version: 2.1
Name: regxtools
Version: 1.0.10
Summary: My short description for my project.
Home-page: https://github.com/me/myproject
Author: Jean M. Girard
Author-email: jean.m.girard@outlook.com
License: MIT
Platform: UNKNOWN
Classifier: License :: OSI Approved :: MIT License
Classifier: Programming Language :: Python
Classifier: Programming Language :: Python :: 3
Classifier: Programming Language :: Python :: 3.6
Classifier: Programming Language :: Python :: Implementation :: CPython
Classifier: Programming Language :: Python :: Implementation :: PyPy
Requires-Python: >=3.6.0
Requires-Dist: reg
Requires-Dist: pyyaml
